[
  {
    "id": 1,
    "option": "EI",
    "question": "到达旅行目的地的第一天晚上，在旅馆里首次遇到其他旅行者，你会有何反应？",
    "answers": [
      {
        "type": "E",
        "content": "打招呼，分享关于旅行的故事。"
      },
      {
        "type": "I",
        "content": "假装没有看见，为了明天的行程早点休息。"
      }
    ]
  },
  {
    "id": 2,
    "option": "EI",
    "question": "乘坐公交车时，你提前一个站下车了，和你一样犯错的同龄人也下车了。你会怎么做？",
    "answers": [
      {
        "type": "E",
        "content": "觉得无聊，和他/她聊天一起走。"
      },
      {
        "type": "I",
        "content": "等车再来，留在车站。"
      }
    ]
  },
  {
    "id": 3,
    "option": "EI",
    "question": "旅行的最后一天，城市举办了盛大的庆祝活动。你会怎么安排？",
    "answers": [
      {
        "type": "E",
        "content": "用庆祝活动来美好地结束我的旅行。"
      },
      {
        "type": "I",
        "content": "再次去我在旅途中喜欢的地方。"
      }
    ]
  },
  {
    "id": 4,
    "option": "SN",
    "question": "在相同价格下，你会选择乘坐耗时较长的夜间火车还是较快的飞机？",
    "answers": [
      {
        "type": "S",
        "content": "当然是较快的飞机，立刻出发。"
      },
      {
        "type": "N",
        "content": "哪有这么浪漫，当然是夜间火车。"
      }
    ]
  },
  {
    "id": 5,
    "which": "SN",
    "question": "在纪念品店，你发现一件非常心仪的纪念品，你会怎么做？",
    "answers": [
      {
        "type": "S",
        "content": "最后不过就是个漂亮的垃圾，还是省省钱吧。"
      },
      {
        "type": "N",
        "content": "这种东西在哪里再买到？当然是马上购买。"
      }
    ]
  },
  {
    "id": 6,
    "which": "SN",
    "question": "在旅行地，一个外国人邀请你参加家庭聚会。你会怎么做？",
    "answers": [
      {
        "type": "S",
        "content": "虽然很感谢，但为了安全起见，还是礼貌地拒绝。"
      },
      {
        "type": "N",
        "content": "哇，有机会体验这种事情真是太兴奋了，当然会去参加。"
      }
    ]
  },
  {
    "id": 7,
    "option": "TF",
    "question": "突然有一个外国人向你借交通费，你会怎么做？",
    "answers": [
      {
        "type": "T",
        "content": "礼貌地表示抱歉并拒绝。"
      },
      {
        "type": "F",
        "content": "心里觉得可怜，给他一些零钱。"
      }
    ]
  },
  {
    "id": 8,
    "option": "TF",
    "question": "错过了去下一个城市的最后一班巴士，你会怎么做？",
    "answers": [
      {
        "type": "T",
        "content": "立刻查询明天的车次。"
      },
      {
        "type": "F",
        "content": "算了，先吃顿饭再说。"
      }
    ]
  },
  {
    "id": 9,
    "option": "TF",
    "question": "在旅行地，你遇到一个你喜欢的异性，你会怎么做？",
    "answers": [
      {
        "type": "T",
        "content": "这只是一个过路人，为了剩下的行程，我会分开。"
      },
      {
        "type": "F",
        "content": "行程不再重要，我想和这个人一起旅行。"
      }
    ]
  },
  {
    "id": 10,
    "option": "JP",
    "question": "独自旅行 VS 与朋友一起旅行，你会选择哪个？",
    "answers": [
      {
        "type": "J",
        "content": "我的英语也不太好，又害怕，与朋友一起更好。"
      },
      {
        "type": "P",
        "content": "独自旅行最舒适和开心。"
      }
    ]
  },
  {
    "id": 11,
    "option": "JP",
    "question": "你的旅行风格是什么？",
    "answers": [
      {
        "type": "J",
        "content": "一分一秒都不能浪费，必须完美地制定行程。"
      },
      {
        "type": "P",
        "content": "只要手机在手，无所畏惧，无需制定计划。"
      }
    ]
  },
  {
    "id": 12,
    "option": "JP",
    "question": "你如何找到独特的美食？",
    "answers": [
      {
        "type": "J",
        "content": "列出美食清单，然后选择去哪家。"
      },
      {
        "type": "P",
        "content": "看到餐厅里有很多人，就进去尝试。"
      }
    ]
  }
]
